MANIFEST.in
README.md
setup.py
secv_guis/__init__.py
secv_guis/__main__.py
secv_guis/base_widgets.py
secv_guis/commands.py
secv_guis/dialogs.py
secv_guis/masked_scene.py
secv_guis/mouse_event_manager.py
secv_guis/objects.py
secv_guis/utils.py
secv_guis.egg-info/PKG-INFO
secv_guis.egg-info/SOURCES.txt
secv_guis.egg-info/dependency_links.txt
secv_guis.egg-info/requires.txt
secv_guis.egg-info/top_level.txt
secv_guis/bimask_app/__init__.py
secv_guis/bimask_app/about.txt
secv_guis/bimask_app/dialogs.py
secv_guis/bimask_app/instructions.txt
secv_guis/bimask_app/main_window.py