Metadata-Version: 2.1
Name: secv-guis
Version: 0.3.1
Summary: Qt GUIs for Systems Engineering and Computer Vision
Home-page: https://github.com/andres-fr/secv-guis
Author: aferro
Author-email: aferro@em.uni-frankfurt.de
License: UNKNOWN
Platform: UNKNOWN
Classifier: Programming Language :: Python :: 3 :: Only
Classifier: License :: OSI Approved :: MIT License
Classifier: Operating System :: OS Independent
